{"frontend_javascript_index.md":"CiDN01pd","frontend_node_index.md":"NQcBc5PO","frontend_javascript_es6.md":"BpDzTyYX","extend_bit.md":"DdbboJ7e","frontend_node_koa.md":"CxXEQcKO","extend_bug.md":"DnArXGdj","frontend_index.md":"Bou4GSHX","frontend_javascript_handwriting.md":"Bi-MDnsN","extend_npm.md":"D96sox7a","frontend_javascript_deepclone.md":"aRK1rzD6","life_seven-provinces.md":"rMTd0FlP","interview_one.md":"Ca3i_cU5","interview_real-question.md":"BGRMEgTk","life_index.md":"G4ehVZ_b","life_friend-lcp.md":"Bp0IoDb6","frontend_node_vite.md":"CuoyCWjI","guide_borwer-message.md":"Dzbe18G6","guide_index.md":"BoMj_8ZO","frontend_html-css_index.md":"DbjLUpqB","frontend_node_webpack4.md":"DyLWICww","interview_overview.md":"CDd_uq8c","guide_es2017-2021.md":"BxQCPlZN","guide_borwer-render.md":"BrQlt5FS","extend_tips.md":"DIr8twGF","frontend_html-css_scroll-into-view.md":"B_66czBn","guide_es6-simplify-code.md":"Dimaca-j","life_xueyue-year2020.md":"BlZeFUE2","guide_event-loop.md":"DR69z9QY","life_xueyue-year2023.md":"CMzRr_9-","frontend_vue_skill.md":"DuwLGkQb","frontend_vue_modifier.md":"WIrl_RMH","frontend_vue_index.md":"B7K-83S-","guide_this.md":"Cl6MQd9n","interview_index.md":"Crp49lZf","frontend_html-css_triangle.md":"CF620qF0","index.md":"Bjg50nUk","extend_markdowm.md":"CLtP3SCq","life_xueyue-age20.md":"5xlwAuX9","guide_standard.md":"ByUretLs","extend_index.md":"CAwQq8fi","guide_prototype.md":"CKlSwcEM","frontend_vue_standard.md":"D1d_7dKC","guide_vite-vue3.md":"CSTYJctK","guide_css-block.md":"BNGYMHDx","guide_chrome-extensions.md":"CQn1ZP5y","extend_git.md":"C00CPDP_","frontend_html-css_element-centered.md":"DXQ9DznR","frontend_html-css_css-style.md":"DblZp45U"}
